cashfree_verification/__init__.py
cashfree_verification/api_client.py
cashfree_verification/api_response.py
cashfree_verification/configuration.py
cashfree_verification/exceptions.py
cashfree_verification/py.typed
cashfree_verification/rest.py
cashfree_verification/models/__init__.py
cashfree_verification/models/aadhaar_masking_response_schema.py
cashfree_verification/models/aadhaar_ocr_request_schema.py
cashfree_verification/models/aadhaar_ocr_response_schema.py
cashfree_verification/models/aadhaarmaskingrequestschema.py
cashfree_verification/models/address_details.py
cashfree_verification/models/address_details_split_address.py
cashfree_verification/models/advance_employment_request_schema.py
cashfree_verification/models/advance_employment_response.py
cashfree_verification/models/advance_employment_response_input.py
cashfree_verification/models/advance_employment_response_recent_employment_details.py
cashfree_verification/models/advance_employment_response_recent_employment_details_employee_details.py
cashfree_verification/models/advance_employment_response_recent_employment_details_employee_details_epfo.py
cashfree_verification/models/advance_employment_response_recent_employment_details_employer_details.py
cashfree_verification/models/advance_employment_response_recent_employment_details_employer_details_pf_filing_details_inner.py
cashfree_verification/models/advance_employment_response_uan_details_inner.py
cashfree_verification/models/advance_employment_response_uan_details_inner_additional_details.py
cashfree_verification/models/advance_employment_response_uan_details_inner_basic_details.py
cashfree_verification/models/advance_employment_response_uan_details_inner_employment_details.py
cashfree_verification/models/badge_details.py
cashfree_verification/models/bulk_pan_request_schema.py
cashfree_verification/models/bulk_pan_request_schema_entries_inner.py
cashfree_verification/models/cin_request_schema.py
cashfree_verification/models/cin_response_schema.py
cashfree_verification-3.0.0.dist-info/METADATA
cashfree_verification-3.0.0.dist-info/WHEEL
cashfree_verification-3.0.0.dist-info/top_level.txt
cashfree_verification-3.0.0.dist-info/RECORD
