Metadata-Version: 2.1
Name: cashfree-verification
Version: 3.0.0
Summary: Cashfree Verification API&#39;s.
Home-page: https://cashfree.com
Author: Cashfree Payments
Author-email: developers@cashfree.com
License: Apache 2.0
Keywords: Payment Gateway,Cashfree,SDK,Payments,Cashfree Verification API's.
Requires-Dist: urllib3<2.1.0,>=1.25.3
Requires-Dist: python-dateutil
Requires-Dist: sentry-sdk<1.33.0,>=1.32.0
Requires-Dist: pydantic<2,>=1.10.5
Requires-Dist: aenum
